inscd_run.py
inscd/__init__.py
inscd/_base.py
inscd/_listener.py
inscd/_ruler.py
inscd/_runner.py
inscd/_unifier.py
inscd/default.yaml
inscd/utils.py
inscd/configs/CDMFKC.yaml
inscd/configs/DCD.yaml
inscd/configs/DCD2.yaml
inscd/configs/DisenGCD.yaml
inscd/configs/HyperCDM.yaml
inscd/configs/ICDM.yaml
inscd/configs/IRT.yaml
inscd/configs/KANCD.yaml
inscd/configs/KSCD.yaml
inscd/configs/MIRT.yaml
inscd/configs/NCDM.yaml
inscd/configs/ORCDF.yaml
inscd/configs/RCD.yaml
inscd/configs/SCD.yaml
inscd/configs/SymbolCD.yaml
inscd/datahub/__init__.py
inscd/datahub/assist17.py
inscd/datahub/datahub.py
inscd/datahub/frcsub.py
inscd/datahub/junyi734.py
inscd/datahub/math1.py
inscd/datahub/math2.py
inscd/datahub/matmat.py
inscd/datahub/neurips20.py
inscd/datahub/utils.py
inscd/datahub/xes3g5m.py
inscd/extractor/__init__.py
inscd/extractor/cdmfkc.py
inscd/extractor/default.py
inscd/extractor/disengcd.py
inscd/extractor/hypercdm.py
inscd/extractor/icdm.py
inscd/extractor/lightgcn.py
inscd/extractor/orcdf.py
inscd/extractor/rcd.py
inscd/extractor/scd.py
inscd/interfunc/__init__.py
inscd/interfunc/_util.py
inscd/interfunc/cdmfkc.py
inscd/interfunc/disengcd.py
inscd/interfunc/dp.py
inscd/interfunc/irt.py
inscd/interfunc/kancd.py
inscd/interfunc/kscd.py
inscd/interfunc/mf.py
inscd/interfunc/mirt.py
inscd/interfunc/ncd.py
inscd/interfunc/rcd.py
inscd/interfunc/scd.py
inscd/models/__init__.py
inscd/models/classical/__init__.py
inscd/models/classical/irt.py
inscd/models/classical/mirt.py
inscd/models/graph/__init__.py
inscd/models/graph/disengcd.py
inscd/models/graph/hypercdm.py
inscd/models/graph/icdm.py
inscd/models/graph/orcdf.py
inscd/models/graph/rcd.py
inscd/models/graph/scd.py
inscd/models/misc/__init__.py
inscd/models/misc/symbolcd.py
inscd/models/misc/_symbolcd/__init__.py
inscd/models/misc/_symbolcd/eval.py
inscd/models/misc/_symbolcd/interaction.py
inscd/models/misc/_symbolcd/model.py
inscd/models/misc/_symbolcd/operators.py
inscd/models/misc/_symbolcd/parameter.py
inscd_tookit-1.3.2.dist-info/LICENSE
inscd_tookit-1.3.2.dist-info/METADATA
inscd_tookit-1.3.2.dist-info/WHEEL
inscd_tookit-1.3.2.dist-info/entry_points.txt
inscd_tookit-1.3.2.dist-info/top_level.txt
inscd_tookit-1.3.2.dist-info/RECORD
